README.md
setup.cfg
setup.py
netbox_fusioninventory_plugin/__init__.py
netbox_fusioninventory_plugin/urls.py
netbox_fusioninventory_plugin/utils.py
netbox_fusioninventory_plugin/views.py
netbox_fusioninventory_plugin_1.egg-info/PKG-INFO
netbox_fusioninventory_plugin_1.egg-info/SOURCES.txt
netbox_fusioninventory_plugin_1.egg-info/dependency_links.txt
netbox_fusioninventory_plugin_1.egg-info/requires.txt
netbox_fusioninventory_plugin_1.egg-info/top_level.txt