Metadata-Version: 2.4
Name: netbox_fusioninventory_plugin_1
Version: 0.8
Summary: A Plugin for import devices from fusion inventory agent
Home-page: https://gitlab.com/Milka64/netbox-fusioninventory-plugin
Author: Michael Ricart
License: BSD License
Requires-Dist: beautifulsoup4
Requires-Dist: lxml
Requires-Dist: unicode-slugify
Dynamic: author
Dynamic: description
Dynamic: description-content-type
Dynamic: home-page
Dynamic: license
Dynamic: requires-dist
Dynamic: summary
